{"type": "GameHistory", "senses": {"true": [19, 47, 1, 47, 29, 15, 23, 18, 54, 0, 61, 51, 0, 55, 45, 25, 4, 21, 26, 28, 44, 60, 8, 63, 13, 54, 60, 47, 32, 17, 6, 37, 31, 41, 27, 28, 22, 28, 26, 3, 39, 18, 37, 14, 16, 7, 47, 38, 10, 54], "false": [13, 8, 25, 29, 29, 19, 20, 15, 35, 38, 30, 39, 26, 41, 3, 18, 48, 7, 47, 34, 41, 21, 61, 53, 2, 43, 23, 42, 0, 10, 29, 10, 28, 29, 10, 7, 30, 35, 7, 47, 62, 37, 27, 51, 21, 27, 39, 35, 52, 7]}, "sense_results": {"true": [[[26, null], [27, null], [28, null], [18, null], [19, null], [20, null], [10, {"type": "Piece", "value": "P"}], [11, {"type": "Piece", "value": "P"}], [12, {"type": "Piece", "value": "P"}]], [[54, {"type": "Piece", "value": "p"}], [55, {"type": "Piece", "value": "p"}], [46, null], [47, {"type": "Piece", "value": "n"}], [38, null], [39, null]], [[8, {"type": "Piece", "value": "P"}], [9, {"type": "Piece", "value": "P"}], [10, {"type": "Piece", "value": "P"}], [0, {"type": "Piece", "value": "R"}], [1, {"type": "Piece", "value": "N"}], [2, {"type": "Piece", "value": "B"}]], [[54, {"type": "Piece", "value": "p"}], [55, {"type": "Piece", "value": "p"}], [46, null], [47, {"type": "Piece", "value": "n"}], [38, null], [39, null]], [[36, null], [37, null], [38, null], [28, null], [29, null], [30, null], [20, null], [21, null], [22, null]], [[22, null], [23, null], [14, {"type": "Piece", "value": "P"}], [15, {"type": "Piece", "value": "P"}], [6, {"type": "Piece", "value": "N"}], [7, {"type": "Piece", "value": "R"}]], [[30, null], [31, null], [22, null], [23, null], [14, {"type": "Piece", "value": "P"}], [15, {"type": "Piece", "value": "P"}]], [[25, null], [26, null], [27, {"type": "Piece", "value": "P"}], [17, {"type": "Piece", "value": "Q"}], [18, {"type": "Piece", "value": "P"}], [19, null], [9, {"type": "Piece", "value": "P"}], [10, null], [11, null]], [[61, {"type": "Piece", "value": "b"}], [62, null], [63, {"type": "Piece", "value": "r"}], [53, null], [54, {"type": "Piece", "value": "p"}], [55, {"type": "Piece", "value": "p"}], [45, {"type": "Piece", "value": "p"}], [46, null], [47, {"type": "Piece", "value": "n"}]], [[8, {"type": "Piece", "value": "P"}], [9, {"type": "Piece", "value": "P"}], [0, {"type": "Piece", "value": "R"}], [1, null]], [[60, {"type": "Piece", "value": "k"}], [61, {"type": "Piece", "value": "b"}], [62, null], [52, {"type": "Piece", "value": "p"}], [53, {"type": "Piece", "value": "n"}], [54, {"type": "Piece", "value": "p"}]], [[58, {"type": "Piece", "value": "b"}], [59, {"type": "Piece", "value": "q"}], [60, {"type": "Piece", "value": "k"}], [50, null], [51, {"type": "Piece", "value": "p"}], [52, {"type": "Piece", "value": "p"}], [42, {"type": "Piece", "value": "p"}], [43, null], [44, null]], [[8, {"type": "Piece", "value": "P"}], [9, {"type": "Piece", "value": "P"}], [0, {"type": "Piece", "value": "R"}], [1, null]], [[62, null], [63, {"type": "Piece", "value": "r"}], [54, {"type": "Piece", "value": "p"}], [55, {"type": "Piece", "value": "p"}], [46, null], [47, null]], [[52, {"type": "Piece", "value": "p"}], [53, {"type": "Piece", "value": "n"}], [54, {"type": "Piece", "value": "p"}], [44, null], [45, {"type": "Piece", "value": "p"}], [46, null], [36, null], [37, null], [38, null]], [[32, null], [33, {"type": "Piece", "value": "p"}], [34, {"type": "Piece", "value": "p"}], [24, null], [25, null], [26, null], [16, {"type": "Piece", "value": "N"}], [17, null], [18, {"type": "Piece", "value": "P"}]], [[11, null], [12, {"type": "Piece", "value": "P"}], [13, null], [3, null], [4, null], [5, {"type": "Piece", "value": "B"}]], [[28, null], [29, {"type": "Piece", "value": "P"}], [30, null], [20, null], [21, null], [22, null], [12, {"type": "Piece", "value": "P"}], [13, null], [14, {"type": "Piece", "value": "P"}]], [[33, {"type": "Piece", "value": "p"}], [34, {"type": "Piece", "value": "p"}], [35, null], [25, null], [26, null], [27, {"type": "Piece", "value": "P"}], [17, null], [18, {"type": "Piece", "value": "P"}], [19, null]], [[35, null], [36, {"type": "Piece", "value": "n"}], [37, null], [27, {"type": "Piece", "value": "P"}], [28, null], [29, {"type": "Piece", "value": "P"}], [19, null], [20, null], [21, null]], [[51, {"type": "Piece", "value": "p"}], [52, {"type": "Piece", "value": "p"}], [53, null], [43, null], [44, null], [45, {"type": "Piece", "value": "p"}], [35, null], [36, null], [37, null]], [[59, null], [60, {"type": "Piece", "value": "k"}], [61, {"type": "Piece", "value": "b"}], [51, {"type": "Piece", "value": "p"}], [52, {"type": "Piece", "value": "p"}], [53, null]], [[16, {"type": "Piece", "value": "N"}], [17, null], [8, {"type": "Piece", "value": "P"}], [9, {"type": "Piece", "value": "P"}], [0, {"type": "Piece", "value": "R"}], [1, null]], [[62, null], [63, {"type": "Piece", "value": "r"}], [54, {"type": "Piece", "value": "p"}], [55, null]], [[20, null], [21, {"type": "Piece", "value": "N"}], [22, null], [12, {"type": "Piece", "value": "P"}], [13, null], [14, null], [4, null], [5, {"type": "Piece", "value": "B"}], [6, null]], [[61, {"type": "Piece", "value": "Q"}], [62, null], [63, {"type": "Piece", "value": "r"}], [53, null], [54, {"type": "Piece", "value": "p"}], [55, null], [45, {"type": "Piece", "value": "p"}], [46, null], [47, {"type": "Piece", "value": "p"}]], [[59, null], [60, {"type": "Piece", "value": "k"}], [61, null], [51, null], [52, null], [53, null]], [[54, {"type": "Piece", "value": "p"}], [55, null], [46, null], [47, {"type": "Piece", "value": "p"}], [38, null], [39, {"type": "Piece", "value": "P"}]], [[40, {"type": "Piece", "value": "n"}], [41, null], [32, null], [33, null], [24, null], [25, {"type": "Piece", "value": "p"}]], [[24, null], [25, {"type": "Piece", "value": "p"}], [26, {"type": "Piece", "value": "N"}], [16, null], [17, null], [18, {"type": "Piece", "value": "P"}], [8, {"type": "Piece", "value": "P"}], [9, {"type": "Piece", "value": "P"}], [10, {"type": "Piece", "value": "K"}]], [[13, null], [14, null], [15, {"type": "Piece", "value": "R"}], [5, {"type": "Piece", "value": "B"}], [6, null], [7, null]], [[44, {"type": "Piece", "value": "k"}], [45, {"type": "Piece", "value": "p"}], [46, null], [36, null], [37, null], [38, null], [28, {"type": "Piece", "value": "P"}], [29, {"type": "Piece", "value": "B"}], [30, {"type": "Piece", "value": "P"}]], [[38, null], [39, {"type": "Piece", "value": "P"}], [30, {"type": "Piece", "value": "P"}], [31, null], [22, null], [23, null]], [[48, null], [49, null], [50, null], [40, {"type": "Piece", "value": "n"}], [41, null], [42, {"type": "Piece", "value": "Q"}], [32, null], [33, null], [34, null]], [[34, null], [35, null], [36, null], [26, {"type": "Piece", "value": "N"}], [27, {"type": "Piece", "value": "P"}], [28, {"type": "Piece", "value": "P"}], [18, {"type": "Piece", "value": "P"}], [19, null], [20, null]], [[35, null], [36, null], [37, null], [27, {"type": "Piece", "value": "P"}], [28, {"type": "Piece", "value": "P"}], [29, null], [19, null], [20, null], [21, {"type": "Piece", "value": "N"}]], [[29, null], [30, {"type": "Piece", "value": "b"}], [31, null], [21, {"type": "Piece", "value": "N"}], [22, null], [23, null], [13, {"type": "Piece", "value": "R"}], [14, null], [15, null]], [[35, null], [36, null], [37, null], [27, {"type": "Piece", "value": "P"}], [28, {"type": "Piece", "value": "P"}], [29, null], [19, null], [20, null], [21, {"type": "Piece", "value": "N"}]], [[33, null], [34, null], [35, null], [25, null], [26, {"type": "Piece", "value": "N"}], [27, {"type": "Piece", "value": "P"}], [17, {"type": "Piece", "value": "P"}], [18, {"type": "Piece", "value": "p"}], [19, null]], [[10, null], [11, null], [12, null], [2, {"type": "Piece", "value": "B"}], [3, null], [4, null]], [[46, null], [47, {"type": "Piece", "value": "r"}], [38, null], [39, {"type": "Piece", "value": "P"}], [30, null], [31, {"type": "Piece", "value": "Q"}]], [[25, null], [26, {"type": "Piece", "value": "N"}], [27, {"type": "Piece", "value": "P"}], [17, {"type": "Piece", "value": "P"}], [18, {"type": "Piece", "value": "p"}], [19, null], [9, {"type": "Piece", "value": "K"}], [10, null], [11, {"type": "Piece", "value": "N"}]], [[44, null], [45, null], [46, null], [36, null], [37, {"type": "Piece", "value": "R"}], [38, null], [28, {"type": "Piece", "value": "P"}], [29, null], [30, null]], [[21, null], [22, null], [23, null], [13, null], [14, {"type": "Piece", "value": "B"}], [15, null], [5, null], [6, null], [7, null]], [[24, null], [25, {"type": "Piece", "value": "r"}], [16, null], [17, {"type": "Piece", "value": "P"}], [8, {"type": "Piece", "value": "P"}], [9, {"type": "Piece", "value": "K"}]], [[14, {"type": "Piece", "value": "B"}], [15, null], [6, null], [7, null]], [[54, {"type": "Piece", "value": "p"}], [55, null], [46, null], [47, null], [38, null], [39, {"type": "Piece", "value": "r"}]], [[45, null], [46, null], [47, null], [37, {"type": "Piece", "value": "R"}], [38, null], [39, {"type": "Piece", "value": "Q"}], [29, null], [30, null], [31, null]], [[17, null], [18, {"type": "Piece", "value": "p"}], [19, null], [9, {"type": "Piece", "value": "K"}], [10, null], [11, {"type": "Piece", "value": "N"}], [1, null], [2, null], [3, null]], [[61, null], [62, null], [63, null], [53, null], [54, {"type": "Piece", "value": "p"}], [55, null], [45, null], [46, null], [47, null]]], "false": [[[20, null], [21, null], [22, null], [12, {"type": "Piece", "value": "P"}], [13, {"type": "Piece", "value": "P"}], [14, {"type": "Piece", "value": "P"}], [4, {"type": "Piece", "value": "K"}], [5, {"type": "Piece", "value": "B"}], [6, {"type": "Piece", "value": "N"}]], [[16, null], [17, null], [8, {"type": "Piece", "value": "P"}], [9, {"type": "Piece", "value": "P"}], [0, {"type": "Piece", "value": "R"}], [1, {"type": "Piece", "value": "N"}]], [[32, null], [33, null], [34, null], [24, null], [25, null], [26, null], [16, null], [17, null], [18, null]], [[36, null], [37, null], [38, null], [28, null], [29, null], [30, null], [20, null], [21, null], [22, null]], [[36, null], [37, null], [38, null], [28, null], [29, null], [30, null], [20, null], [21, null], [22, null]], [[26, null], [27, {"type": "Piece", "value": "P"}], [28, null], [18, {"type": "Piece", "value": "P"}], [19, null], [20, null], [10, null], [11, null], [12, {"type": "Piece", "value": "P"}]], [[27, {"type": "Piece", "value": "P"}], [28, null], [29, null], [19, null], [20, null], [21, null], [11, null], [12, {"type": "Piece", "value": "P"}], [13, {"type": "Piece", "value": "P"}]], [[22, null], [23, null], [14, {"type": "Piece", "value": "P"}], [15, {"type": "Piece", "value": "P"}], [6, {"type": "Piece", "value": "N"}], [7, {"type": "Piece", "value": "R"}]], [[42, null], [43, null], [44, null], [34, null], [35, null], [36, null], [26, null], [27, {"type": "Piece", "value": "P"}], [28, null]], [[45, {"type": "Piece", "value": "p"}], [46, null], [47, null], [37, null], [38, null], [39, null], [29, {"type": "Piece", "value": "P"}], [30, null], [31, null]], [[37, null], [38, null], [39, null], [29, {"type": "Piece", "value": "P"}], [30, null], [31, null], [21, null], [22, null], [23, null]], [[46, null], [47, null], [38, null], [39, null], [30, null], [31, null]], [[33, {"type": "Piece", "value": "p"}], [34, {"type": "Piece", "value": "p"}], [35, {"type": "Piece", "value": "Q"}], [25, null], [26, null], [27, {"type": "Piece", "value": "P"}], [17, null], [18, {"type": "Piece", "value": "P"}], [19, null]], [[48, {"type": "Piece", "value": "p"}], [49, null], [50, {"type": "Piece", "value": "q"}], [40, {"type": "Piece", "value": "n"}], [41, null], [42, null], [32, null], [33, {"type": "Piece", "value": "p"}], [34, {"type": "Piece", "value": "p"}]], [[10, {"type": "Piece", "value": "K"}], [11, null], [12, {"type": "Piece", "value": "P"}], [2, {"type": "Piece", "value": "B"}], [3, null], [4, null]], [[25, null], [26, null], [27, {"type": "Piece", "value": "P"}], [17, null], [18, {"type": "Piece", "value": "P"}], [19, null], [9, {"type": "Piece", "value": "P"}], [10, {"type": "Piece", "value": "K"}], [11, null]], [[56, null], [57, {"type": "Piece", "value": "r"}], [48, {"type": "Piece", "value": "Q"}], [49, null], [40, {"type": "Piece", "value": "n"}], [41, null]], [[14, null], [15, null], [6, {"type": "Piece", "value": "N"}], [7, {"type": "Piece", "value": "R"}]], [[54, {"type": "Piece", "value": "p"}], [55, {"type": "Piece", "value": "p"}], [46, null], [47, null], [38, null], [39, null]], [[41, null], [42, null], [43, null], [33, null], [34, {"type": "Piece", "value": "Q"}], [35, null], [25, {"type": "Piece", "value": "p"}], [26, null], [27, {"type": "Piece", "value": "P"}]], [[48, null], [49, {"type": "Piece", "value": "q"}], [50, null], [40, {"type": "Piece", "value": "n"}], [41, null], [42, null], [32, null], [33, null], [34, {"type": "Piece", "value": "Q"}]], [[28, null], [29, {"type": "Piece", "value": "P"}], [30, {"type": "Piece", "value": "P"}], [20, null], [21, {"type": "Piece", "value": "N"}], [22, null], [12, {"type": "Piece", "value": "P"}], [13, null], [14, null]], [[60, {"type": "Piece", "value": "k"}], [61, {"type": "Piece", "value": "Q"}], [62, null], [52, null], [53, null], [54, {"type": "Piece", "value": "p"}]], [[60, {"type": "Piece", "value": "k"}], [61, {"type": "Piece", "value": "Q"}], [62, null], [52, null], [53, null], [54, {"type": "Piece", "value": "p"}], [44, null], [45, {"type": "Piece", "value": "p"}], [46, null]], [[9, {"type": "Piece", "value": "P"}], [10, {"type": "Piece", "value": "K"}], [11, null], [1, null], [2, {"type": "Piece", "value": "B"}], [3, null]], [[50, null], [51, null], [52, null], [42, null], [43, {"type": "Piece", "value": "Q"}], [44, null], [34, null], [35, null], [36, null]], [[30, {"type": "Piece", "value": "P"}], [31, null], [22, null], [23, null], [14, null], [15, {"type": "Piece", "value": "R"}]], [[49, null], [50, null], [51, null], [41, null], [42, {"type": "Piece", "value": "Q"}], [43, null], [33, null], [34, null], [35, null]], [[8, {"type": "Piece", "value": "P"}], [9, {"type": "Piece", "value": "P"}], [0, {"type": "Piece", "value": "R"}], [1, null]], [[17, null], [18, {"type": "Piece", "value": "P"}], [19, null], [9, {"type": "Piece", "value": "P"}], [10, {"type": "Piece", "value": "K"}], [11, null], [1, null], [2, {"type": "Piece", "value": "B"}], [3, null]], [[36, null], [37, null], [38, null], [28, {"type": "Piece", "value": "P"}], [29, {"type": "Piece", "value": "B"}], [30, {"type": "Piece", "value": "P"}], [20, null], [21, {"type": "Piece", "value": "N"}], [22, null]], [[17, {"type": "Piece", "value": "P"}], [18, {"type": "Piece", "value": "P"}], [19, null], [9, null], [10, {"type": "Piece", "value": "K"}], [11, null], [1, null], [2, null], [3, null]], [[35, null], [36, null], [37, null], [27, {"type": "Piece", "value": "P"}], [28, {"type": "Piece", "value": "P"}], [29, null], [19, null], [20, null], [21, {"type": "Piece", "value": "N"}]], [[36, null], [37, null], [38, null], [28, {"type": "Piece", "value": "P"}], [29, null], [30, {"type": "Piece", "value": "b"}], [20, null], [21, {"type": "Piece", "value": "N"}], [22, null]], [[17, {"type": "Piece", "value": "P"}], [18, {"type": "Piece", "value": "P"}], [19, null], [9, null], [10, {"type": "Piece", "value": "K"}], [11, null], [1, null], [2, {"type": "Piece", "value": "B"}], [3, null]], [[14, null], [15, null], [6, null], [7, null]], [[37, null], [38, null], [39, {"type": "Piece", "value": "P"}], [29, null], [30, {"type": "Piece", "value": "Q"}], [31, null], [21, {"type": "Piece", "value": "N"}], [22, null], [23, null]], [[42, null], [43, null], [44, null], [34, null], [35, null], [36, null], [26, {"type": "Piece", "value": "N"}], [27, {"type": "Piece", "value": "P"}], [28, {"type": "Piece", "value": "P"}]], [[14, null], [15, null], [6, null], [7, null]], [[54, {"type": "Piece", "value": "p"}], [55, {"type": "Piece", "value": "r"}], [46, null], [47, {"type": "Piece", "value": "B"}], [38, null], [39, {"type": "Piece", "value": "P"}]], [[61, null], [62, null], [63, null], [53, null], [54, {"type": "Piece", "value": "p"}], [55, null]], [[44, null], [45, null], [46, null], [36, null], [37, {"type": "Piece", "value": "R"}], [38, null], [28, {"type": "Piece", "value": "P"}], [29, null], [30, null]], [[34, null], [35, null], [36, null], [26, {"type": "Piece", "value": "N"}], [27, {"type": "Piece", "value": "P"}], [28, {"type": "Piece", "value": "P"}], [18, {"type": "Piece", "value": "p"}], [19, null], [20, null]], [[58, null], [59, null], [60, null], [50, null], [51, null], [52, null], [42, null], [43, {"type": "Piece", "value": "k"}], [44, null]], [[28, {"type": "Piece", "value": "P"}], [29, null], [30, null], [20, null], [21, null], [22, null], [12, null], [13, null], [14, {"type": "Piece", "value": "B"}]], [[34, null], [35, null], [36, null], [26, {"type": "Piece", "value": "N"}], [27, {"type": "Piece", "value": "P"}], [28, {"type": "Piece", "value": "P"}], [18, {"type": "Piece", "value": "p"}], [19, null], [20, null]], [[46, null], [47, null], [38, null], [39, {"type": "Piece", "value": "Q"}], [30, null], [31, null]], [[42, null], [43, null], [44, null], [34, null], [35, null], [36, null], [26, {"type": "Piece", "value": "N"}], [27, {"type": "Piece", "value": "P"}], [28, {"type": "Piece", "value": "P"}]], [[59, null], [60, null], [61, null], [51, {"type": "Piece", "value": "k"}], [52, null], [53, null], [43, null], [44, null], [45, null]], [[14, {"type": "Piece", "value": "B"}], [15, null], [6, null], [7, null]]]}, "requested_moves": {"true": [{"type": "Move", "value": "g2h3"}, null, {"type": "Move", "value": "d2d4"}, {"type": "Move", "value": "d4e5"}, {"type": "Move", "value": "c2c3"}, {"type": "Move", "value": "d1b3"}, {"type": "Move", "value": "e2f3"}, {"type": "Move", "value": "b1a3"}, {"type": "Move", "value": "f2f4"}, {"type": "Move", "value": "e1d1"}, {"type": "Move", "value": "d1d2"}, {"type": "Move", "value": "d2c2"}, {"type": "Move", "value": "b3d5"}, {"type": "Move", "value": "h2h4"}, {"type": "Move", "value": "d5b7"}, {"type": "Move", "value": "e2f3"}, {"type": "Move", "value": "b7a7"}, {"type": "Move", "value": "g2g4"}, {"type": "Move", "value": "h4g5"}, {"type": "Move", "value": "a7c5"}, {"type": "Move", "value": "f4g5"}, {"type": "Move", "value": "g1f3"}, {"type": "Move", "value": "c5f8"}, {"type": "Move", "value": "h4h5"}, {"type": "Move", "value": "e2d3"}, {"type": "Move", "value": "f8d6"}, {"type": "Move", "value": "h1h2"}, {"type": "Move", "value": "d6b6"}, {"type": "Move", "value": "a3c4"}, {"type": "Move", "value": "e2e4"}, {"type": "Move", "value": "c1g5"}, {"type": "Move", "value": "b2b4"}, {"type": "Move", "value": "f4c1"}, {"type": "Move", "value": "c6c8"}, {"type": "Move", "value": "h2f2"}, {"type": "Move", "value": "c2b2"}, {"type": "Move", "value": "c8g4"}, {"type": "Move", "value": "h5h6"}, {"type": "Move", "value": "g4h4"}, {"type": "Move", "value": "c1h6"}, {"type": "Move", "value": "f3d2"}, {"type": "Move", "value": "f2f8"}, {"type": "Move", "value": "f1g2"}, {"type": "Move", "value": "h5g6"}, {"type": "Move", "value": "a1f1"}, {"type": "Move", "value": "h5g6"}, {"type": "Move", "value": "h4h6"}, {"type": "Move", "value": "h5h4"}, {"type": "Move", "value": "h4f4"}, {"type": "Move", "value": "c4e3"}], "false": [{"type": "Move", "value": "g8h6"}, {"type": "Move", "value": "g7f6"}, {"type": "Move", "value": "e7f6"}, {"type": "Move", "value": "f7e6"}, {"type": "Move", "value": "f7f6"}, {"type": "Move", "value": "b8a6"}, {"type": "Move", "value": "d7c6"}, {"type": "Move", "value": "b7b5"}, {"type": "Move", "value": "h6f7"}, {"type": "Move", "value": "c7c6"}, {"type": "Move", "value": "a8b8"}, {"type": "Move", "value": "c6c5"}, {"type": "Move", "value": "d8c7"}, {"type": "Move", "value": "g7h6"}, null, {"type": "Move", "value": "f7e5"}, {"type": "Move", "value": "c7b7"}, {"type": "Move", "value": "f6g5"}, {"type": "Move", "value": "b5b4"}, {"type": "Move", "value": "e5f3"}, {"type": "Move", "value": "h7h6"}, {"type": "Move", "value": "e7e5"}, {"type": "Move", "value": "d7e6"}, {"type": "Move", "value": "e5f4"}, {"type": "Move", "value": "d7d6"}, {"type": "Move", "value": "b7c6"}, {"type": "Move", "value": "e8e7"}, {"type": "Move", "value": "e7e6"}, {"type": "Move", "value": "h8e8"}, {"type": "Move", "value": "e8d8"}, {"type": "Move", "value": "d8e8"}, {"type": "Move", "value": "e6e7"}, {"type": "Move", "value": "c8g4"}, {"type": "Move", "value": "e7d8"}, {"type": "Move", "value": "e8h8"}, null, {"type": "Move", "value": "h8h7"}, {"type": "Move", "value": "b4c3"}, {"type": "Move", "value": "f6f5"}, {"type": "Move", "value": "h7h4"}, {"type": "Move", "value": "d8c7"}, {"type": "Move", "value": "b8b4"}, {"type": "Move", "value": "c7d6"}, {"type": "Move", "value": "h6h7"}, {"type": "Move", "value": "d6d7"}, {"type": "Move", "value": "h7h5"}, {"type": "Move", "value": "b4b1"}, {"type": "Move", "value": "b3b6"}, {"type": "Move", "value": "a6b4"}, {"type": "Move", "value": "c3b2"}]}, "taken_moves": {"true": [null, null, {"type": "Move", "value": "d2d4"}, null, {"type": "Move", "value": "c2c3"}, {"type": "Move", "value": "d1b3"}, null, {"type": "Move", "value": "b1a3"}, {"type": "Move", "value": "f2f4"}, {"type": "Move", "value": "e1d1"}, {"type": "Move", "value": "d1d2"}, {"type": "Move", "value": "d2c2"}, {"type": "Move", "value": "b3d5"}, {"type": "Move", "value": "h2h4"}, {"type": "Move", "value": "d5b7"}, null, {"type": "Move", "value": "b7a7"}, {"type": "Move", "value": "g2g4"}, null, {"type": "Move", "value": "a7c5"}, null, {"type": "Move", "value": "g1f3"}, {"type": "Move", "value": "c5f8"}, {"type": "Move", "value": "h4h5"}, null, {"type": "Move", "value": "f8d6"}, {"type": "Move", "value": "h1h2"}, {"type": "Move", "value": "d6c6"}, {"type": "Move", "value": "a3c4"}, {"type": "Move", "value": "e2e4"}, {"type": "Move", "value": "c1f4"}, {"type": "Move", "value": "b2b3"}, {"type": "Move", "value": "f4c1"}, {"type": "Move", "value": "c6c8"}, {"type": "Move", "value": "h2f2"}, {"type": "Move", "value": "c2b2"}, {"type": "Move", "value": "c8g4"}, null, {"type": "Move", "value": "g4h4"}, {"type": "Move", "value": "c1h6"}, {"type": "Move", "value": "f3d2"}, {"type": "Move", "value": "f2f5"}, {"type": "Move", "value": "f1g2"}, null, {"type": "Move", "value": "a1f1"}, null, {"type": "Move", "value": "h4h5"}, {"type": "Move", "value": "h5h4"}, {"type": "Move", "value": "h4f4"}, {"type": "Move", "value": "c4e3"}], "false": [{"type": "Move", "value": "g8h6"}, null, null, null, {"type": "Move", "value": "f7f6"}, {"type": "Move", "value": "b8a6"}, null, {"type": "Move", "value": "b7b5"}, {"type": "Move", "value": "h6f7"}, {"type": "Move", "value": "c7c6"}, {"type": "Move", "value": "a8b8"}, {"type": "Move", "value": "c6c5"}, {"type": "Move", "value": "d8c7"}, null, null, {"type": "Move", "value": "f7e5"}, {"type": "Move", "value": "c7b7"}, null, {"type": "Move", "value": "b5b4"}, {"type": "Move", "value": "e5f3"}, {"type": "Move", "value": "h7h6"}, {"type": "Move", "value": "e7e5"}, null, {"type": "Move", "value": "e5f4"}, {"type": "Move", "value": "d7d6"}, {"type": "Move", "value": "b7c6"}, {"type": "Move", "value": "e8e7"}, {"type": "Move", "value": "e7e6"}, {"type": "Move", "value": "h8e8"}, {"type": "Move", "value": "e8d8"}, {"type": "Move", "value": "d8e8"}, {"type": "Move", "value": "e6e7"}, {"type": "Move", "value": "c8g4"}, {"type": "Move", "value": "e7d8"}, {"type": "Move", "value": "e8h8"}, null, {"type": "Move", "value": "h8h7"}, {"type": "Move", "value": "b4c3"}, {"type": "Move", "value": "f6f5"}, {"type": "Move", "value": "h7h6"}, {"type": "Move", "value": "d8c7"}, {"type": "Move", "value": "b8b4"}, {"type": "Move", "value": "c7d6"}, {"type": "Move", "value": "h6h7"}, {"type": "Move", "value": "d6d7"}, {"type": "Move", "value": "h7h5"}, {"type": "Move", "value": "b4b3"}, {"type": "Move", "value": "b3b6"}, {"type": "Move", "value": "a6b4"}, {"type": "Move", "value": "c3b2"}]}, "capture_squares": {"true": [null, null, null, null, null, null, null, null, null, null, null, null, null, null, null, null, 48, null, null, 34, null, 21, 61, null, null, 43, null, 42, null, null, 29, null, null, null, null, null, 30, null, null, 47, null, 37, null, null, null, null, 39, null, null, null], "false": [null, null, null, null, null, null, null, null, null, null, null, null, null, null, null, null, null, null, null, null, null, null, null, 29, null, null, null, null, null, null, null, null, 30, null, null, null, null, 18, null, 47, null, null, null, null, null, 39, 17, null, null, 9]}, "fens_before_move": {"true": ["rnbqkbnr/pppppppp/8/8/8/8/PPPPPPPP/RNBQKBNR w KQkq - 0 1", "rnbqkb1r/pppppppp/7n/8/8/8/PPPPPPPP/RNBQKBNR w KQkq - 2 2", "rnbqkb1r/pppppppp/7n/8/8/8/PPPPPPPP/RNBQKBNR w KQkq - 4 3", "rnbqkb1r/pppppppp/7n/8/3P4/8/PPP1PPPP/RNBQKBNR w KQkq - 1 4", "rnbqkb1r/pppppppp/7n/8/3P4/8/PPP1PPPP/RNBQKBNR w KQkq - 3 5", "rnbqkb1r/ppppp1pp/5p1n/8/3P4/2P5/PP2PPPP/RNBQKBNR w KQkq - 0 6", "r1bqkb1r/ppppp1pp/n4p1n/8/3P4/1QP5/PP2PPPP/RNB1KBNR w KQkq - 2 7", "r1bqkb1r/ppppp1pp/n4p1n/8/3P4/1QP5/PP2PPPP/RNB1KBNR w KQkq - 4 8", "r1bqkb1r/p1ppp1pp/n4p1n/1p6/3P4/NQP5/PP2PPPP/R1B1KBNR w KQkq - 0 9", "r1bqkb1r/p1pppnpp/n4p2/1p6/3P1P2/NQP5/PP2P1PP/R1B1KBNR w KQkq - 1 10", "r1bqkb1r/p2ppnpp/n1p2p2/1p6/3P1P2/NQP5/PP2P1PP/R1BK1BNR w kq - 0 11", "1rbqkb1r/p2ppnpp/n1p2p2/1p6/3P1P2/NQP5/PP1KP1PP/R1B2BNR w k - 2 12", "1rbqkb1r/p2ppnpp/n4p2/1pp5/3P1P2/NQP5/PPK1P1PP/R1B2BNR w k - 0 13", "1rb1kb1r/p1qppnpp/n4p2/1ppQ4/3P1P2/N1P5/PPK1P1PP/R1B2BNR w k - 2 14", "1rb1kb1r/p1qppnpp/n4p2/1ppQ4/3P1P1P/N1P5/PPK1P1P1/R1B2BNR w k - 1 15", "1rb1kb1r/pQqppnpp/n4p2/1pp5/3P1P1P/N1P5/PPK1P1P1/R1B2BNR w k - 3 16", "1rb1kb1r/pQqpp1pp/n4p2/1pp1n3/3P1P1P/N1P5/PPK1P1P1/R1B2BNR w k - 5 17", "1rb1kb1r/Qq1pp1pp/n4p2/1pp1n3/3P1P1P/N1P5/PPK1P1P1/R1B2BNR w k - 1 18", "1rb1kb1r/Qq1pp1pp/n4p2/1pp1n3/3P1PPP/N1P5/PPK1P3/R1B2BNR w k - 1 19", "1rb1kb1r/Qq1pp1pp/n4p2/2p1n3/1p1P1PPP/N1P5/PPK1P3/R1B2BNR w k - 0 20", "1rb1kb1r/1q1pp1pp/n4p2/2Q5/1p1P1PPP/N1P2n2/PPK1P3/R1B2BNR w k - 1 21", "1rb1kb1r/1q1pp1p1/n4p1p/2Q5/1p1P1PPP/N1P2n2/PPK1P3/R1B2BNR w k - 0 22", "1rb1kb1r/1q1p2p1/n4p1p/2Q1p3/1p1P1PPP/N1P2N2/PPK1P3/R1B2B1R w k - 0 23", "1rb1kQ1r/1q1p2p1/n4p1p/4p3/1p1P1PPP/N1P2N2/PPK1P3/R1B2B1R w k - 1 24", "1rb1kQ1r/1q1p2p1/n4p1p/7P/1p1P1pP1/N1P2N2/PPK1P3/R1B2B1R w k - 0 25", "1rb1kQ1r/1q4p1/n2p1p1p/7P/1p1P1pP1/N1P2N2/PPK1P3/R1B2B1R w k - 0 26", "1rb1k2r/6p1/n1qQ1p1p/7P/1p1P1pP1/N1P2N2/PPK1P3/R1B2B1R w k - 1 27", "1rb4r/4k1p1/n1qQ1p1p/7P/1p1P1pP1/N1P2N2/PPK1P2R/R1B2B2 w - - 3 28", "1rb4r/6p1/n1Q1kp1p/7P/1p1P1pP1/N1P2N2/PPK1P2R/R1B2B2 w - - 1 29", "1rb1r3/6p1/n1Q1kp1p/7P/1pNP1pP1/2P2N2/PPK1P2R/R1B2B2 w - - 3 30", "1rbr4/6p1/n1Q1kp1p/7P/1pNPPpP1/2P2N2/PPK4R/R1B2B2 w - - 1 31", "1rb1r3/6p1/n1Q1kp1p/7P/1pNPPBP1/2P2N2/PPK4R/R4B2 w - - 1 32", "1rb1r3/4k1p1/n1Q2p1p/7P/1pNPPBP1/1PP2N2/P1K4R/R4B2 w - - 1 33", "1r2r3/4k1p1/n1Q2p1p/7P/1pNPP1b1/1PP2N2/P1K4R/R1B2B2 w - - 0 34", "1rQkr3/6p1/n4p1p/7P/1pNPP1b1/1PP2N2/P1K4R/R1B2B2 w - - 2 35", "1rQk3r/6p1/n4p1p/7P/1pNPP1b1/1PP2N2/P1K2R2/R1B2B2 w - - 4 36", "1rQk3r/6p1/n4p1p/7P/1pNPP1b1/1PP2N2/PK3R2/R1B2B2 w - - 6 37", "1r1k4/6pr/n4p1p/7P/1pNPP1Q1/1PP2N2/PK3R2/R1B2B2 w - - 1 38", "1r1k4/6pr/n4p1p/7P/2NPP1Q1/1Pp2N2/PK3R2/R1B2B2 w - - 0 39", "1r1k4/6pr/n6p/5p1P/2NPP2Q/1Pp2N2/PK3R2/R1B2B2 w - - 0 40", "1r1k4/6p1/n6r/5p1P/2NPP2Q/1Pp2N2/PK3R2/R4B2 w - - 0 41", "1r6/2k3p1/n6r/5p1P/2NPP2Q/1Pp5/PK1N1R2/R4B2 w - - 2 42", "8/2k3p1/n6r/5R1P/1rNPP2Q/1Pp5/PK1N4/R4B2 w - - 1 43", "8/6p1/n2k3r/5R1P/1rNPP2Q/1Pp5/PK1N2B1/R7 w - - 3 44", "8/6pr/n2k4/5R1P/1rNPP2Q/1Pp5/PK1N2B1/R7 w - - 5 45", "8/3k2pr/n7/5R1P/1rNPP2Q/1Pp5/PK1N2B1/5R2 w - - 7 46", "8/3k2p1/n7/5R1r/1rNPP2Q/1Pp5/PK1N2B1/5R2 w - - 0 47", "8/3k2p1/n7/5R1Q/2NPP3/1rp5/PK1N2B1/5R2 w - - 0 48", "8/3k2p1/nr6/5R2/2NPP2Q/2p5/PK1N2B1/5R2 w - - 2 49", "8/3k2p1/1r6/5R2/1nNPPQ2/2p5/PK1N2B1/5R2 w - - 4 50"], "false": ["rnbqkbnr/pppppppp/8/8/8/8/PPPPPPPP/RNBQKBNR b KQkq - 1 1", "rnbqkb1r/pppppppp/7n/8/8/8/PPPPPPPP/RNBQKBNR b KQkq - 3 2", "rnbqkb1r/pppppppp/7n/8/3P4/8/PPP1PPPP/RNBQKBNR b KQkq - 0 3", "rnbqkb1r/pppppppp/7n/8/3P4/8/PPP1PPPP/RNBQKBNR b KQkq - 2 4", "rnbqkb1r/pppppppp/7n/8/3P4/2P5/PP2PPPP/RNBQKBNR b KQkq - 0 5", "rnbqkb1r/ppppp1pp/5p1n/8/3P4/1QP5/PP2PPPP/RNB1KBNR b KQkq - 1 6", "r1bqkb1r/ppppp1pp/n4p1n/8/3P4/1QP5/PP2PPPP/RNB1KBNR b KQkq - 3 7", "r1bqkb1r/ppppp1pp/n4p1n/8/3P4/NQP5/PP2PPPP/R1B1KBNR b KQkq - 5 8", "r1bqkb1r/p1ppp1pp/n4p1n/1p6/3P1P2/NQP5/PP2P1PP/R1B1KBNR b KQkq - 0 9", "r1bqkb1r/p1pppnpp/n4p2/1p6/3P1P2/NQP5/PP2P1PP/R1BK1BNR b kq - 2 10", "r1bqkb1r/p2ppnpp/n1p2p2/1p6/3P1P2/NQP5/PP1KP1PP/R1B2BNR b kq - 1 11", "1rbqkb1r/p2ppnpp/n1p2p2/1p6/3P1P2/NQP5/PPK1P1PP/R1B2BNR b k - 3 12", "1rbqkb1r/p2ppnpp/n4p2/1ppQ4/3P1P2/N1P5/PPK1P1PP/R1B2BNR b k - 1 13", "1rb1kb1r/p1qppnpp/n4p2/1ppQ4/3P1P1P/N1P5/PPK1P1P1/R1B2BNR b k - 0 14", "1rb1kb1r/pQqppnpp/n4p2/1pp5/3P1P1P/N1P5/PPK1P1P1/R1B2BNR b k - 2 15", "1rb1kb1r/pQqppnpp/n4p2/1pp5/3P1P1P/N1P5/PPK1P1P1/R1B2BNR b k - 4 16", "1rb1kb1r/Q1qpp1pp/n4p2/1pp1n3/3P1P1P/N1P5/PPK1P1P1/R1B2BNR b k - 0 17", "1rb1kb1r/Qq1pp1pp/n4p2/1pp1n3/3P1PPP/N1P5/PPK1P3/R1B2BNR b k - 0 18", "1rb1kb1r/Qq1pp1pp/n4p2/1pp1n3/3P1PPP/N1P5/PPK1P3/R1B2BNR b k - 2 19", "1rb1kb1r/1q1pp1pp/n4p2/2Q1n3/1p1P1PPP/N1P5/PPK1P3/R1B2BNR b k - 0 20", "1rb1kb1r/1q1pp1pp/n4p2/2Q5/1p1P1PPP/N1P2n2/PPK1P3/R1B2BNR b k - 2 21", "1rb1kb1r/1q1pp1p1/n4p1p/2Q5/1p1P1PPP/N1P2N2/PPK1P3/R1B2B1R b k - 0 22", "1rb1kQ1r/1q1p2p1/n4p1p/4p3/1p1P1PPP/N1P2N2/PPK1P3/R1B2B1R b k - 0 23", "1rb1kQ1r/1q1p2p1/n4p1p/4p2P/1p1P1PP1/N1P2N2/PPK1P3/R1B2B1R b k - 0 24", "1rb1kQ1r/1q1p2p1/n4p1p/7P/1p1P1pP1/N1P2N2/PPK1P3/R1B2B1R b k - 1 25", "1rb1k2r/1q4p1/n2Q1p1p/7P/1p1P1pP1/N1P2N2/PPK1P3/R1B2B1R b k - 0 26", "1rb1k2r/6p1/n1qQ1p1p/7P/1p1P1pP1/N1P2N2/PPK1P2R/R1B2B2 b k - 2 27", "1rb4r/4k1p1/n1Q2p1p/7P/1p1P1pP1/N1P2N2/PPK1P2R/R1B2B2 b - - 0 28", "1rb4r/6p1/n1Q1kp1p/7P/1pNP1pP1/2P2N2/PPK1P2R/R1B2B2 b - - 2 29", "1rb1r3/6p1/n1Q1kp1p/7P/1pNPPpP1/2P2N2/PPK4R/R1B2B2 b - - 0 30", "1rbr4/6p1/n1Q1kp1p/7P/1pNPPBP1/2P2N2/PPK4R/R4B2 b - - 0 31", "1rb1r3/6p1/n1Q1kp1p/7P/1pNPPBP1/1PP2N2/P1K4R/R4B2 b - - 0 32", "1rb1r3/4k1p1/n1Q2p1p/7P/1pNPP1P1/1PP2N2/P1K4R/R1B2B2 b - - 2 33", "1rQ1r3/4k1p1/n4p1p/7P/1pNPP1b1/1PP2N2/P1K4R/R1B2B2 b - - 1 34", "1rQkr3/6p1/n4p1p/7P/1pNPP1b1/1PP2N2/P1K2R2/R1B2B2 b - - 3 35", "1rQk3r/6p1/n4p1p/7P/1pNPP1b1/1PP2N2/PK3R2/R1B2B2 b - - 5 36", "1r1k3r/6p1/n4p1p/7P/1pNPP1Q1/1PP2N2/PK3R2/R1B2B2 b - - 0 37", "1r1k4/6pr/n4p1p/7P/1pNPP1Q1/1PP2N2/PK3R2/R1B2B2 b - - 2 38", "1r1k4/6pr/n4p1p/7P/2NPP2Q/1Pp2N2/PK3R2/R1B2B2 b - - 1 39", "1r1k4/6pr/n6B/5p1P/2NPP2Q/1Pp2N2/PK3R2/R4B2 b - - 0 40", "1r1k4/6p1/n6r/5p1P/2NPP2Q/1Pp5/PK1N1R2/R4B2 b - - 1 41", "1r6/2k3p1/n6r/5R1P/2NPP2Q/1Pp5/PK1N4/R4B2 b - - 0 42", "8/2k3p1/n6r/5R1P/1rNPP2Q/1Pp5/PK1N2B1/R7 b - - 2 43", "8/6p1/n2k3r/5R1P/1rNPP2Q/1Pp5/PK1N2B1/R7 b - - 4 44", "8/6pr/n2k4/5R1P/1rNPP2Q/1Pp5/PK1N2B1/5R2 b - - 6 45", "8/3k2pr/n7/5R1P/1rNPP2Q/1Pp5/PK1N2B1/5R2 b - - 8 46", "8/3k2p1/n7/5R1Q/1rNPP3/1Pp5/PK1N2B1/5R2 b - - 0 47", "8/3k2p1/n7/5R2/2NPP2Q/1rp5/PK1N2B1/5R2 b - - 1 48", "8/3k2p1/nr6/5R2/2NPPQ2/2p5/PK1N2B1/5R2 b - - 3 49", "8/3k2p1/1r6/5R2/1n1PPQ2/2p1N3/PK1N2B1/5R2 b - - 5 50"]}, "fens_after_move": {"true": ["rnbqkbnr/pppppppp/8/8/8/8/PPPPPPPP/RNBQKBNR b KQkq - 1 1", "rnbqkb1r/pppppppp/7n/8/8/8/PPPPPPPP/RNBQKBNR b KQkq - 3 2", "rnbqkb1r/pppppppp/7n/8/3P4/8/PPP1PPPP/RNBQKBNR b KQkq - 0 3", "rnbqkb1r/pppppppp/7n/8/3P4/8/PPP1PPPP/RNBQKBNR b KQkq - 2 4", "rnbqkb1r/pppppppp/7n/8/3P4/2P5/PP2PPPP/RNBQKBNR b KQkq - 0 5", "rnbqkb1r/ppppp1pp/5p1n/8/3P4/1QP5/PP2PPPP/RNB1KBNR b KQkq - 1 6", "r1bqkb1r/ppppp1pp/n4p1n/8/3P4/1QP5/PP2PPPP/RNB1KBNR b KQkq - 3 7", "r1bqkb1r/ppppp1pp/n4p1n/8/3P4/NQP5/PP2PPPP/R1B1KBNR b KQkq - 5 8", "r1bqkb1r/p1ppp1pp/n4p1n/1p6/3P1P2/NQP5/PP2P1PP/R1B1KBNR b KQkq - 0 9", "r1bqkb1r/p1pppnpp/n4p2/1p6/3P1P2/NQP5/PP2P1PP/R1BK1BNR b kq - 2 10", "r1bqkb1r/p2ppnpp/n1p2p2/1p6/3P1P2/NQP5/PP1KP1PP/R1B2BNR b kq - 1 11", "1rbqkb1r/p2ppnpp/n1p2p2/1p6/3P1P2/NQP5/PPK1P1PP/R1B2BNR b k - 3 12", "1rbqkb1r/p2ppnpp/n4p2/1ppQ4/3P1P2/N1P5/PPK1P1PP/R1B2BNR b k - 1 13", "1rb1kb1r/p1qppnpp/n4p2/1ppQ4/3P1P1P/N1P5/PPK1P1P1/R1B2BNR b k - 0 14", "1rb1kb1r/pQqppnpp/n4p2/1pp5/3P1P1P/N1P5/PPK1P1P1/R1B2BNR b k - 2 15", "1rb1kb1r/pQqppnpp/n4p2/1pp5/3P1P1P/N1P5/PPK1P1P1/R1B2BNR b k - 4 16", "1rb1kb1r/Q1qpp1pp/n4p2/1pp1n3/3P1P1P/N1P5/PPK1P1P1/R1B2BNR b k - 0 17", "1rb1kb1r/Qq1pp1pp/n4p2/1pp1n3/3P1PPP/N1P5/PPK1P3/R1B2BNR b k - 0 18", "1rb1kb1r/Qq1pp1pp/n4p2/1pp1n3/3P1PPP/N1P5/PPK1P3/R1B2BNR b k - 2 19", "1rb1kb1r/1q1pp1pp/n4p2/2Q1n3/1p1P1PPP/N1P5/PPK1P3/R1B2BNR b k - 0 20", "1rb1kb1r/1q1pp1pp/n4p2/2Q5/1p1P1PPP/N1P2n2/PPK1P3/R1B2BNR b k - 2 21", "1rb1kb1r/1q1pp1p1/n4p1p/2Q5/1p1P1PPP/N1P2N2/PPK1P3/R1B2B1R b k - 0 22", "1rb1kQ1r/1q1p2p1/n4p1p/4p3/1p1P1PPP/N1P2N2/PPK1P3/R1B2B1R b k - 0 23", "1rb1kQ1r/1q1p2p1/n4p1p/4p2P/1p1P1PP1/N1P2N2/PPK1P3/R1B2B1R b k - 0 24", "1rb1kQ1r/1q1p2p1/n4p1p/7P/1p1P1pP1/N1P2N2/PPK1P3/R1B2B1R b k - 1 25", "1rb1k2r/1q4p1/n2Q1p1p/7P/1p1P1pP1/N1P2N2/PPK1P3/R1B2B1R b k - 0 26", "1rb1k2r/6p1/n1qQ1p1p/7P/1p1P1pP1/N1P2N2/PPK1P2R/R1B2B2 b k - 2 27", "1rb4r/4k1p1/n1Q2p1p/7P/1p1P1pP1/N1P2N2/PPK1P2R/R1B2B2 b - - 0 28", "1rb4r/6p1/n1Q1kp1p/7P/1pNP1pP1/2P2N2/PPK1P2R/R1B2B2 b - - 2 29", "1rb1r3/6p1/n1Q1kp1p/7P/1pNPPpP1/2P2N2/PPK4R/R1B2B2 b - - 0 30", "1rbr4/6p1/n1Q1kp1p/7P/1pNPPBP1/2P2N2/PPK4R/R4B2 b - - 0 31", "1rb1r3/6p1/n1Q1kp1p/7P/1pNPPBP1/1PP2N2/P1K4R/R4B2 b - - 0 32", "1rb1r3/4k1p1/n1Q2p1p/7P/1pNPP1P1/1PP2N2/P1K4R/R1B2B2 b - - 2 33", "1rQ1r3/4k1p1/n4p1p/7P/1pNPP1b1/1PP2N2/P1K4R/R1B2B2 b - - 1 34", "1rQkr3/6p1/n4p1p/7P/1pNPP1b1/1PP2N2/P1K2R2/R1B2B2 b - - 3 35", "1rQk3r/6p1/n4p1p/7P/1pNPP1b1/1PP2N2/PK3R2/R1B2B2 b - - 5 36", "1r1k3r/6p1/n4p1p/7P/1pNPP1Q1/1PP2N2/PK3R2/R1B2B2 b - - 0 37", "1r1k4/6pr/n4p1p/7P/1pNPP1Q1/1PP2N2/PK3R2/R1B2B2 b - - 2 38", "1r1k4/6pr/n4p1p/7P/2NPP2Q/1Pp2N2/PK3R2/R1B2B2 b - - 1 39", "1r1k4/6pr/n6B/5p1P/2NPP2Q/1Pp2N2/PK3R2/R4B2 b - - 0 40", "1r1k4/6p1/n6r/5p1P/2NPP2Q/1Pp5/PK1N1R2/R4B2 b - - 1 41", "1r6/2k3p1/n6r/5R1P/2NPP2Q/1Pp5/PK1N4/R4B2 b - - 0 42", "8/2k3p1/n6r/5R1P/1rNPP2Q/1Pp5/PK1N2B1/R7 b - - 2 43", "8/6p1/n2k3r/5R1P/1rNPP2Q/1Pp5/PK1N2B1/R7 b - - 4 44", "8/6pr/n2k4/5R1P/1rNPP2Q/1Pp5/PK1N2B1/5R2 b - - 6 45", "8/3k2pr/n7/5R1P/1rNPP2Q/1Pp5/PK1N2B1/5R2 b - - 8 46", "8/3k2p1/n7/5R1Q/1rNPP3/1Pp5/PK1N2B1/5R2 b - - 0 47", "8/3k2p1/n7/5R2/2NPP2Q/1rp5/PK1N2B1/5R2 b - - 1 48", "8/3k2p1/nr6/5R2/2NPPQ2/2p5/PK1N2B1/5R2 b - - 3 49", "8/3k2p1/1r6/5R2/1n1PPQ2/2p1N3/PK1N2B1/5R2 b - - 5 50"], "false": ["rnbqkb1r/pppppppp/7n/8/8/8/PPPPPPPP/RNBQKBNR w KQkq - 2 2", "rnbqkb1r/pppppppp/7n/8/8/8/PPPPPPPP/RNBQKBNR w KQkq - 4 3", "rnbqkb1r/pppppppp/7n/8/3P4/8/PPP1PPPP/RNBQKBNR w KQkq - 1 4", "rnbqkb1r/pppppppp/7n/8/3P4/8/PPP1PPPP/RNBQKBNR w KQkq - 3 5", "rnbqkb1r/ppppp1pp/5p1n/8/3P4/2P5/PP2PPPP/RNBQKBNR w KQkq - 0 6", "r1bqkb1r/ppppp1pp/n4p1n/8/3P4/1QP5/PP2PPPP/RNB1KBNR w KQkq - 2 7", "r1bqkb1r/ppppp1pp/n4p1n/8/3P4/1QP5/PP2PPPP/RNB1KBNR w KQkq - 4 8", "r1bqkb1r/p1ppp1pp/n4p1n/1p6/3P4/NQP5/PP2PPPP/R1B1KBNR w KQkq - 0 9", "r1bqkb1r/p1pppnpp/n4p2/1p6/3P1P2/NQP5/PP2P1PP/R1B1KBNR w KQkq - 1 10", "r1bqkb1r/p2ppnpp/n1p2p2/1p6/3P1P2/NQP5/PP2P1PP/R1BK1BNR w kq - 0 11", "1rbqkb1r/p2ppnpp/n1p2p2/1p6/3P1P2/NQP5/PP1KP1PP/R1B2BNR w k - 2 12", "1rbqkb1r/p2ppnpp/n4p2/1pp5/3P1P2/NQP5/PPK1P1PP/R1B2BNR w k - 0 13", "1rb1kb1r/p1qppnpp/n4p2/1ppQ4/3P1P2/N1P5/PPK1P1PP/R1B2BNR w k - 2 14", "1rb1kb1r/p1qppnpp/n4p2/1ppQ4/3P1P1P/N1P5/PPK1P1P1/R1B2BNR w k - 1 15", "1rb1kb1r/pQqppnpp/n4p2/1pp5/3P1P1P/N1P5/PPK1P1P1/R1B2BNR w k - 3 16", "1rb1kb1r/pQqpp1pp/n4p2/1pp1n3/3P1P1P/N1P5/PPK1P1P1/R1B2BNR w k - 5 17", "1rb1kb1r/Qq1pp1pp/n4p2/1pp1n3/3P1P1P/N1P5/PPK1P1P1/R1B2BNR w k - 1 18", "1rb1kb1r/Qq1pp1pp/n4p2/1pp1n3/3P1PPP/N1P5/PPK1P3/R1B2BNR w k - 1 19", "1rb1kb1r/Qq1pp1pp/n4p2/2p1n3/1p1P1PPP/N1P5/PPK1P3/R1B2BNR w k - 0 20", "1rb1kb1r/1q1pp1pp/n4p2/2Q5/1p1P1PPP/N1P2n2/PPK1P3/R1B2BNR w k - 1 21", "1rb1kb1r/1q1pp1p1/n4p1p/2Q5/1p1P1PPP/N1P2n2/PPK1P3/R1B2BNR w k - 0 22", "1rb1kb1r/1q1p2p1/n4p1p/2Q1p3/1p1P1PPP/N1P2N2/PPK1P3/R1B2B1R w k - 0 23", "1rb1kQ1r/1q1p2p1/n4p1p/4p3/1p1P1PPP/N1P2N2/PPK1P3/R1B2B1R w k - 1 24", "1rb1kQ1r/1q1p2p1/n4p1p/7P/1p1P1pP1/N1P2N2/PPK1P3/R1B2B1R w k - 0 25", "1rb1kQ1r/1q4p1/n2p1p1p/7P/1p1P1pP1/N1P2N2/PPK1P3/R1B2B1R w k - 0 26", "1rb1k2r/6p1/n1qQ1p1p/7P/1p1P1pP1/N1P2N2/PPK1P3/R1B2B1R w k - 1 27", "1rb4r/4k1p1/n1qQ1p1p/7P/1p1P1pP1/N1P2N2/PPK1P2R/R1B2B2 w - - 3 28", "1rb4r/6p1/n1Q1kp1p/7P/1p1P1pP1/N1P2N2/PPK1P2R/R1B2B2 w - - 1 29", "1rb1r3/6p1/n1Q1kp1p/7P/1pNP1pP1/2P2N2/PPK1P2R/R1B2B2 w - - 3 30", "1rbr4/6p1/n1Q1kp1p/7P/1pNPPpP1/2P2N2/PPK4R/R1B2B2 w - - 1 31", "1rb1r3/6p1/n1Q1kp1p/7P/1pNPPBP1/2P2N2/PPK4R/R4B2 w - - 1 32", "1rb1r3/4k1p1/n1Q2p1p/7P/1pNPPBP1/1PP2N2/P1K4R/R4B2 w - - 1 33", "1r2r3/4k1p1/n1Q2p1p/7P/1pNPP1b1/1PP2N2/P1K4R/R1B2B2 w - - 0 34", "1rQkr3/6p1/n4p1p/7P/1pNPP1b1/1PP2N2/P1K4R/R1B2B2 w - - 2 35", "1rQk3r/6p1/n4p1p/7P/1pNPP1b1/1PP2N2/P1K2R2/R1B2B2 w - - 4 36", "1rQk3r/6p1/n4p1p/7P/1pNPP1b1/1PP2N2/PK3R2/R1B2B2 w - - 6 37", "1r1k4/6pr/n4p1p/7P/1pNPP1Q1/1PP2N2/PK3R2/R1B2B2 w - - 1 38", "1r1k4/6pr/n4p1p/7P/2NPP1Q1/1Pp2N2/PK3R2/R1B2B2 w - - 0 39", "1r1k4/6pr/n6p/5p1P/2NPP2Q/1Pp2N2/PK3R2/R1B2B2 w - - 0 40", "1r1k4/6p1/n6r/5p1P/2NPP2Q/1Pp2N2/PK3R2/R4B2 w - - 0 41", "1r6/2k3p1/n6r/5p1P/2NPP2Q/1Pp5/PK1N1R2/R4B2 w - - 2 42", "8/2k3p1/n6r/5R1P/1rNPP2Q/1Pp5/PK1N4/R4B2 w - - 1 43", "8/6p1/n2k3r/5R1P/1rNPP2Q/1Pp5/PK1N2B1/R7 w - - 3 44", "8/6pr/n2k4/5R1P/1rNPP2Q/1Pp5/PK1N2B1/R7 w - - 5 45", "8/3k2pr/n7/5R1P/1rNPP2Q/1Pp5/PK1N2B1/5R2 w - - 7 46", "8/3k2p1/n7/5R1r/1rNPP2Q/1Pp5/PK1N2B1/5R2 w - - 0 47", "8/3k2p1/n7/5R1Q/2NPP3/1rp5/PK1N2B1/5R2 w - - 0 48", "8/3k2p1/nr6/5R2/2NPP2Q/2p5/PK1N2B1/5R2 w - - 2 49", "8/3k2p1/1r6/5R2/1nNPPQ2/2p5/PK1N2B1/5R2 w - - 4 50", "8/3k2p1/1r6/5R2/1n1PPQ2/4N3/Pp1N2B1/5R2 w - - 0 51"]}}